setup.cfg
setup.py
aprsfi/__init__.py
aprsfi/api.py
aprsfi/entry.py
aprsfi/response.py
aprsfi.egg-info/PKG-INFO
aprsfi.egg-info/SOURCES.txt
aprsfi.egg-info/dependency_links.txt
aprsfi.egg-info/requires.txt
aprsfi.egg-info/top_level.txt