Metadata-Version: 1.1
Name: aprsfi
Version: 0.2
Summary: python client aprs.fi API.
Home-page: https://github.com/SAEG-DSE/aprsfi
Author: Whanderley Souza Freitas
Author-email: whanderley.souza@iff.edu.br
License: LGPLv3
Download-URL: https://github.com/SAEG-DSE/python-aprsfi/archive/0.2.tar.gz
Keywords: aprsfi api client wrapper
Platform: UNKNOWN
